odoo9_addon_stock_orderpoint_uom-9.0.1.0.0.99.dev10-py2.7-nspkg.pth
odoo9_addon_stock_orderpoint_uom-9.0.1.0.0.99.dev10.dist-info/METADATA
odoo9_addon_stock_orderpoint_uom-9.0.1.0.0.99.dev10.dist-info/RECORD
odoo9_addon_stock_orderpoint_uom-9.0.1.0.0.99.dev10.dist-info/WHEEL
odoo9_addon_stock_orderpoint_uom-9.0.1.0.0.99.dev10.dist-info/namespace_packages.txt
odoo9_addon_stock_orderpoint_uom-9.0.1.0.0.99.dev10.dist-info/top_level.txt
odoo_addons/stock_orderpoint_uom/README.rst
odoo_addons/stock_orderpoint_uom/__init__.py
odoo_addons/stock_orderpoint_uom/__openerp__.py
odoo_addons/stock_orderpoint_uom/i18n/de.po
odoo_addons/stock_orderpoint_uom/i18n/es.po
odoo_addons/stock_orderpoint_uom/i18n/es_ES.po
odoo_addons/stock_orderpoint_uom/i18n/es_MX.po
odoo_addons/stock_orderpoint_uom/i18n/fr.po
odoo_addons/stock_orderpoint_uom/i18n/hr.po
odoo_addons/stock_orderpoint_uom/i18n/it.po
odoo_addons/stock_orderpoint_uom/i18n/pt_BR.po
odoo_addons/stock_orderpoint_uom/i18n/pt_PT.po
odoo_addons/stock_orderpoint_uom/i18n/ro.po
odoo_addons/stock_orderpoint_uom/i18n/sk.po
odoo_addons/stock_orderpoint_uom/i18n/sl.po
odoo_addons/stock_orderpoint_uom/i18n/stock_orderpoint_uom.pot
odoo_addons/stock_orderpoint_uom/i18n/tr_TR.po
odoo_addons/stock_orderpoint_uom/i18n/vi_VN.po
odoo_addons/stock_orderpoint_uom/i18n/zh_CN.po
odoo_addons/stock_orderpoint_uom/models/__init__.py
odoo_addons/stock_orderpoint_uom/models/procurement_order.py
odoo_addons/stock_orderpoint_uom/models/stock_warehouse_orderpoint.py
odoo_addons/stock_orderpoint_uom/static/description/icon.png
odoo_addons/stock_orderpoint_uom/tests/__init__.py
odoo_addons/stock_orderpoint_uom/tests/test_stock_orderpoint_procure_uom.py
odoo_addons/stock_orderpoint_uom/views/stock_warehouse_orderpoint_view.xml
