Metadata-Version: 2.1
Name: odoo9-addon-stock-orderpoint-uom
Version: 9.0.1.0.0.99.dev10
Summary: Allows to create procurement orders in the UoM indicated in the orderpoint
Home-page: https://www.odoo-community.org
Author: Eficent Business and IT Consulting Services S.L,Odoo Community Association (OCA)
Author-email: support@odoo-community.org
License: AGPL-3
Platform: UNKNOWN
Classifier: Programming Language :: Python
Classifier: Framework :: Odoo
Classifier: License :: OSI Approved :: GNU Affero General Public License v3
Requires-Python: ~=2.7
Requires-Dist: odoo (<9.1a,>=9.0a)
